{
  "a_name": "DrawData",
  "a_viewport": [
    0,
    0,
    850000,
    1843000
  ],
  "objects": [
    {
      "a_name": "DrawData_default",
      "a_pagePos": [
        0,
        0
      ],
      "datas": [
        {
          "paths": [
            {
              "brush": {
                "color": "#FFFFFF",
                "style": 1
              },
              "mode": 1,
              "path": {
                "elements": [
                  [
                    0,
                    0,
                    0
                  ],
                  [
                    1,
                    850393,
                    0
                  ],
                  [
                    1,
                    850393,
                    1842519
                  ],
                  [
                    1,
                    0,
                    1842519
                  ],
                  [
                    1,
                    0,
                    0
                  ]
                ],
                "fillRule": 0
              },
              "pen": {
                "capStyle": 16,
                "color": "#000000",
                "dashPattern": [],
                "joinStyle": 64,
                "style": 0,
                "width": 1
              }
            }
          ],
          "state": 0
        },
        {
          "state": 1,
          "texts": [
            {
              "flags": 0,
              "point": [
                2000,
                0
              ],
              "text": "2"
            }
          ]
        },
        {
          "polygons": [
            {
              "mode": 3,
              "polygon": [
                [
                  2232,
                  -1364
                ],
                [
                  2232,
                  100576
                ]
              ]
            }
          ],
          "state": 2
        },
        {
          "polygons": [
            {
              "mode": 3,
              "polygon": [
                [
                  20462,
                  -1364
                ],
                [
                  20462,
                  100576
                ]
              ]
            }
          ],
          "state": 3
        },
        {
          "polygons": [
            {
              "mode": 3,
              "polygon": [
                [
                  2232,
                  -1364
                ],
                [
                  2232,
                  100576
                ]
              ]
            }
          ],
          "state": 4
        },
        {
          "polygons": [
            {
              "mode": 3,
              "polygon": [
                [
                  0,
                  0
                ],
                [
                  425196,
                  0
                ]
              ]
            },
            {
              "mode": 3,
              "polygon": [
                [
                  0,
                  24803
                ],
                [
                  425196,
                  24803
                ]
              ]
            },
            {
              "mode": 3,
              "polygon": [
                [
                  0,
                  49606
                ],
                [
                  425196,
                  49606
                ]
              ]
            },
            {
              "mode": 3,
              "polygon": [
                [
                  0,
                  74409
                ],
                [
                  425196,
                  74409
                ]
              ]
            },
            {
              "mode": 3,
              "polygon": [
                [
                  0,
                  99212
                ],
                [
                  425196,
                  99212
                ]
              ]
            }
          ],
          "state": 5
        },
        {
          "polygons": [
            {
              "mode": 3,
              "polygon": [
                [
                  0,
                  0
                ],
                [
                  542338,
                  0
                ]
              ]
            },
            {
              "mode": 3,
              "polygon": [
                [
                  0,
                  24803
                ],
                [
                  542338,
                  24803
                ]
              ]
            },
            {
              "mode": 3,
              "polygon": [
                [
                  0,
                  49606
                ],
                [
                  542338,
                  49606
                ]
              ]
            },
            {
              "mode": 3,
              "polygon": [
                [
                  0,
                  74409
                ],
                [
                  542338,
                  74409
                ]
              ]
            },
            {
              "mode": 3,
              "polygon": [
                [
                  0,
                  99212
                ],
                [
                  542338,
                  99212
                ]
              ]
            }
          ],
          "state": 6
        },
        {
          "state": 7,
          "texts": [
            {
              "flags": 0,
              "point": [
                0,
                0
              ],
              "text": ""
            }
          ]
        },
        {
          "state": 8,
          "texts": [
            {
              "flags": 0,
              "point": [
                0,
                0
              ],
              "text": ""
            }
          ]
        },
        {
          "state": 9,
          "texts": [
            {
              "flags": 0,
              "point": [
                0,
                25000
              ],
              "text": ""
            }
          ]
        },
        {
          "state": 9,
          "texts": [
            {
              "flags": 0,
              "point": [
                0,
                75000
              ],
              "text": ""
            }
          ]
        },
        {
          "state": 10,
          "texts": [
            {
              "flags": 0,
              "point": [
                -2000,
                0
              ],
              "text": "On"
            }
          ]
        },
        {
          "state": 11,
          "texts": [
            {
              "flags": 0,
              "point": [
                -1000,
                0
              ],
              "text": "Invisible"
            }
          ]
        },
        {
          "state": 12,
          "texts": [
            {
              "flags": 0,
              "point": [
                -1000,
                0
              ],
              "text": "Harmony"
            }
          ]
        },
        {
          "state": 13,
          "texts": [
            {
              "flags": 0,
              "point": [
                -2000,
                0
              ],
              "text": "C"
            }
          ]
        },
        {
          "state": 13,
          "texts": [
            {
              "flags": 0,
              "point": [
                36554,
                0
              ],
              "text": "hords"
            }
          ]
        }
      ]
    }
  ],
  "states": {
    "0": {
      "brush": {
        "color": "#FFFFFF",
        "style": 1
      },
      "compositionMode": 0,
      "font": {
        "family": "",
        "hinting": 0,
        "italic": false,
        "no_merging": true,
        "pointSize": -1,
        "type": 0,
        "weight": 50
      },
      "isAntialiasing": true,
      "pen": {
        "capStyle": 16,
        "color": "#000000",
        "dashPattern": [],
        "joinStyle": 64,
        "style": 0,
        "width": 1
      },
      "transform": [
        1000,
        0,
        0,
        0,
        1000,
        0,
        0,
        0,
        1000
      ]
    },
    "1": {
      "brush": {
        "color": "#000000",
        "style": 0
      },
      "compositionMode": 0,
      "font": {
        "family": "Edwin",
        "hinting": 0,
        "italic": true,
        "no_merging": true,
        "pointSize": 8,
        "type": 1,
        "weight": 50
      },
      "isAntialiasing": true,
      "pen": {
        "capStyle": 16,
        "color": "#000000",
        "dashPattern": [],
        "joinStyle": 64,
        "style": 1,
        "width": 1
      },
      "transform": [
        1000,
        0,
        0,
        0,
        1000,
        0,
        212598,
        944291,
        1000
      ]
    },
    "10": {
      "brush": {
        "color": "#000000",
        "style": 0
      },
      "compositionMode": 0,
      "font": {
        "family": "Edwin",
        "hinting": 0,
        "italic": false,
        "no_merging": true,
        "pointSize": 9.92126,
        "type": 1,
        "weight": 50
      },
      "isAntialiasing": true,
      "pen": {
        "capStyle": 16,
        "color": "#000000",
        "dashPattern": [],
        "joinStyle": 64,
        "style": 1,
        "width": 1
      },
      "transform": [
        1000,
        0,
        0,
        0,
        1000,
        0,
        356694,
        931889,
        1000
      ]
    },
    "11": {
      "brush": {
        "color": "#000000",
        "style": 0
      },
      "compositionMode": 0,
      "font": {
        "family": "Edwin",
        "hinting": 0,
        "italic": false,
        "no_merging": true,
        "pointSize": 9.92126,
        "type": 1,
        "weight": 50
      },
      "isAntialiasing": true,
      "pen": {
        "capStyle": 16,
        "color": "#000000",
        "dashPattern": [],
        "joinStyle": 64,
        "style": 1,
        "width": 1
      },
      "transform": [
        1000,
        0,
        0,
        0,
        1000,
        0,
        436094,
        931889,
        1000
      ]
    },
    "12": {
      "brush": {
        "color": "#000000",
        "style": 0
      },
      "compositionMode": 0,
      "font": {
        "family": "Edwin",
        "hinting": 0,
        "italic": false,
        "no_merging": true,
        "pointSize": 9.92126,
        "type": 1,
        "weight": 50
      },
      "isAntialiasing": true,
      "pen": {
        "capStyle": 16,
        "color": "#000000",
        "dashPattern": [],
        "joinStyle": 64,
        "style": 1,
        "width": 1
      },
      "transform": [
        1000,
        0,
        0,
        0,
        1000,
        0,
        411555,
        324212,
        1000
      ]
    },
    "13": {
      "brush": {
        "color": "#000000",
        "style": 0
      },
      "compositionMode": 0,
      "font": {
        "family": "Edwin",
        "hinting": 0,
        "italic": false,
        "no_merging": true,
        "pointSize": 9.92126,
        "type": 1,
        "weight": 50
      },
      "isAntialiasing": true,
      "pen": {
        "capStyle": 16,
        "color": "#000000",
        "dashPattern": [],
        "joinStyle": 64,
        "style": 1,
        "width": 1
      },
      "transform": [
        1000,
        0,
        0,
        0,
        1000,
        0,
        648494,
        931889,
        1000
      ]
    },
    "2": {
      "brush": {
        "color": "#000000",
        "style": 0
      },
      "compositionMode": 0,
      "font": {
        "family": "Edwin",
        "hinting": 0,
        "italic": true,
        "no_merging": true,
        "pointSize": 8,
        "type": 1,
        "weight": 50
      },
      "isAntialiasing": true,
      "pen": {
        "capStyle": 0,
        "color": "#000000",
        "dashPattern": [],
        "joinStyle": 64,
        "style": 1,
        "width": 4.464567
      },
      "transform": [
        1000,
        0,
        0,
        0,
        1000,
        0,
        727653,
        993897,
        1000
      ]
    },
    "3": {
      "brush": {
        "color": "#000000",
        "style": 0
      },
      "compositionMode": 0,
      "font": {
        "family": "Edwin",
        "hinting": 0,
        "italic": true,
        "no_merging": true,
        "pointSize": 8,
        "type": 1,
        "weight": 50
      },
      "isAntialiasing": true,
      "pen": {
        "capStyle": 0,
        "color": "#000000",
        "dashPattern": [],
        "joinStyle": 64,
        "style": 1,
        "width": 13.641732
      },
      "transform": [
        1000,
        0,
        0,
        0,
        1000,
        0,
        727653,
        993897,
        1000
      ]
    },
    "4": {
      "brush": {
        "color": "#000000",
        "style": 0
      },
      "compositionMode": 0,
      "font": {
        "family": "Edwin",
        "hinting": 0,
        "italic": true,
        "no_merging": true,
        "pointSize": 8,
        "type": 1,
        "weight": 50
      },
      "isAntialiasing": true,
      "pen": {
        "capStyle": 0,
        "color": "#000000",
        "dashPattern": [],
        "joinStyle": 64,
        "style": 1,
        "width": 4.464567
      },
      "transform": [
        1000,
        0,
        0,
        0,
        1000,
        0,
        633330,
        386220,
        1000
      ]
    },
    "5": {
      "brush": {
        "color": "#000000",
        "style": 0
      },
      "compositionMode": 0,
      "font": {
        "family": "Edwin",
        "hinting": 0,
        "italic": true,
        "no_merging": true,
        "pointSize": 8,
        "type": 1,
        "weight": 50
      },
      "isAntialiasing": true,
      "pen": {
        "capStyle": 0,
        "color": "#000000",
        "dashPattern": [],
        "joinStyle": 64,
        "style": 1,
        "width": 2.728346
      },
      "transform": [
        1000,
        0,
        0,
        0,
        1000,
        0,
        212598,
        386220,
        1000
      ]
    },
    "6": {
      "brush": {
        "color": "#000000",
        "style": 0
      },
      "compositionMode": 0,
      "font": {
        "family": "Edwin",
        "hinting": 0,
        "italic": true,
        "no_merging": true,
        "pointSize": 8,
        "type": 1,
        "weight": 50
      },
      "isAntialiasing": true,
      "pen": {
        "capStyle": 0,
        "color": "#000000",
        "dashPattern": [],
        "joinStyle": 64,
        "style": 1,
        "width": 2.728346
      },
      "transform": [
        1000,
        0,
        0,
        0,
        1000,
        0,
        212598,
        993897,
        1000
      ]
    },
    "7": {
      "brush": {
        "color": "#000000",
        "style": 0
      },
      "compositionMode": 0,
      "font": {
        "family": "Leland",
        "hinting": 2,
        "italic": false,
        "no_merging": true,
        "pointSize": 20,
        "type": 5,
        "weight": 50
      },
      "isAntialiasing": true,
      "pen": {
        "capStyle": 16,
        "color": "#000000",
        "dashPattern": [],
        "joinStyle": 64,
        "style": 1,
        "width": 1
      },
      "transform": [
        992,
        0,
        0,
        0,
        992,
        0,
        231198,
        1068307,
        1000
      ]
    },
    "8": {
      "brush": {
        "color": "#000000",
        "style": 0
      },
      "compositionMode": 0,
      "font": {
        "family": "Leland",
        "hinting": 2,
        "italic": false,
        "no_merging": true,
        "pointSize": 20,
        "type": 5,
        "weight": 50
      },
      "isAntialiasing": true,
      "pen": {
        "capStyle": 16,
        "color": "#000000",
        "dashPattern": [],
        "joinStyle": 64,
        "style": 1,
        "width": 1
      },
      "transform": [
        992,
        0,
        0,
        0,
        992,
        0,
        231200,
        460629,
        1000
      ]
    },
    "9": {
      "brush": {
        "color": "#000000",
        "style": 0
      },
      "compositionMode": 0,
      "font": {
        "family": "Leland",
        "hinting": 2,
        "italic": false,
        "no_merging": true,
        "pointSize": 20,
        "type": 5,
        "weight": 50
      },
      "isAntialiasing": true,
      "pen": {
        "capStyle": 16,
        "color": "#000000",
        "dashPattern": [],
        "joinStyle": 64,
        "style": 1,
        "width": 1
      },
      "transform": [
        992,
        0,
        0,
        0,
        992,
        0,
        318101,
        386220,
        1000
      ]
    }
  }
}
